haystack_threshold_node/__init__.py
haystack_threshold_node-0.0.1.dist-info/METADATA
haystack_threshold_node-0.0.1.dist-info/WHEEL
haystack_threshold_node-0.0.1.dist-info/licenses/LICENSE
haystack_threshold_node-0.0.1.dist-info/RECORD
