Metadata-Version: 2.1
Name: haystack_threshold_node
Version: 0.0.1
Summary: This component filters documents based on a threshold percentage, ensuring only the documents above the threshold get passed down the pipeline
Project-URL: Homepage, https://github.com/recrudesce/haystack_threshold_node
Project-URL: Bug Tracker, https://github.com/recrudesce/haystack_threshold_node/issues
Author-email: recrudesce <recrudesce@gmail.com>
License-File: LICENSE
Classifier: License :: OSI Approved :: MIT License
Classifier: Operating System :: OS Independent
Classifier: Programming Language :: Python :: 3
Requires-Python: >=3.10
Requires-Dist: farm-haystack
